{
    "name": "REKABIT",
    "description": "",
    "dependencies": {
        "core": "*",
        "microphone": "*",
        "pxt-esp8266": "github:cytrontechnologies/pxt-esp8266#v1.1.4",
        "pxt-rekabit": "github:cytrontechnologies/pxt-rekabit#v1.2.2",
        "Huskylens": "github:dfrobot/pxt-dfrobot_huskylens#v2.0.5"
    },
    "files": [
        "main.blocks",
        "main.ts",
        "README.md"
    ],
    "testFiles": [
        "test.ts"
    ],
    "targetVersions": {
        "target": "5.0.12",
        "targetId": "microbit"
    },
    "supportedTargets": [
        "microbit"
    ],
    "preferredEditor": "blocksprj"
}
